{
  "paper_id": "sha256-eabe48b38ae7610a",
  "library_root": "/Users/brandani/Dropbox/documents/library",
  "pdf_path": "/Users/brandani/Dropbox/documents/library/articles/p53_aggregation/Wilcken 2012 PNAS - Kinetic mechanism of p53 oncogenic mutant aggregation and its inhibition.pdf",
  "pdf_sha256": "eabe48b38ae7610a9ff92a9784032f5848f321da390a704ea688213bdb329a9e",
  "filename": "Wilcken 2012 PNAS -kinetic-mechanism-of-p53-oncogenic-mutant-aggregation-and-its-inhibition.pdf",
  "item_type": "article",
  "title_query": "kinetic mechanism of p53 oncogenic mutant aggregation and its inhibition",
  "filename_hints": {
    "year_hint": 2012,
    "venue_hint": "proceedingsofthenationalacademyofsciences",
    "prefix": "Wilcken 2012 PNAS -kinetic-mechanism-of-p53-oncogenic-mutant-aggregation-and-its-inhibition"
  },
  "doi_candidates": [
    "10.1073/pnas.1211550109/-/DCSupplemental"
  ],
  "date_indexed": "2026-04-17T03:34:58.141862+00:00",
  "match_status": "matched",
  "match_confidence": 1.0,
  "warnings": [],
  "crossref_warnings": [],
  "metadata_source": "semantic_scholar",
  "semantic_scholar": {
    "query": "kinetic mechanism of p53 oncogenic mutant aggregation and its inhibition",
    "limit": 10,
    "api_error": "",
    "best_candidate": {
      "paperId": "e58a39cc21aedc818df66aa14225321977d74b2d",
      "externalIds": {
        "MAG": "1986503899",
        "DOI": "10.1073/pnas.1211550109",
        "CorpusId": 11093198,
        "PubMed": "22869713"
      },
      "url": "https://www.semanticscholar.org/paper/e58a39cc21aedc818df66aa14225321977d74b2d",
      "title": "Kinetic mechanism of p53 oncogenic mutant aggregation and its inhibition",
      "venue": "Proceedings of the National Academy of Sciences of the United States of America",
      "year": 2012,
      "openAccessPdf": {
        "url": "https://www.pnas.org/content/pnas/109/34/13584.full.pdf",
        "status": "BRONZE",
        "license": null,
        "disclaimer": "Notice: The following paper fields have been elided by the publisher: {'abstract'}. Paper or abstract available at https://api.unpaywall.org/v2/10.1073/pnas.1211550109?email=<INSERT_YOUR_EMAIL> or https://doi.org/10.1073/pnas.1211550109, which is subject to the license by the author or copyright owner provided with this content. Please go to the source to verify the license and copyright information for your use."
      },
      "publicationTypes": [
        "JournalArticle"
      ],
      "publicationDate": "2012-08-06",
      "journal": {
        "name": "Proceedings of the National Academy of Sciences",
        "pages": "13584 - 13589",
        "volume": "109"
      },
      "authors": [
        {
          "authorId": "2268524",
          "name": "R. Wilcken"
        },
        {
          "authorId": "2145472159",
          "name": "Guozhen Wang"
        },
        {
          "authorId": "1831601",
          "name": "F. Boeckler"
        },
        {
          "authorId": "2384961",
          "name": "A. Fersht"
        }
      ],
      "abstract": null
    },
    "candidate_scores": [
      {
        "paper_id": "e58a39cc21aedc818df66aa14225321977d74b2d",
        "title": "Kinetic mechanism of p53 oncogenic mutant aggregation and its inhibition",
        "score": 1.0,
        "title_similarity": 1.0,
        "query_year": 2012,
        "candidate_year": 2012,
        "year_bonus": 0.08,
        "author_bonus": 0.04,
        "venue_penalty": 0.0
      }
    ],
    "candidate_dois": [
      "10.1073/pnas.1211550109"
    ],
    "matching_extracted_doi": "",
    "raw_response": {
      "total": 1,
      "offset": 0,
      "data": [
        {
          "paperId": "e58a39cc21aedc818df66aa14225321977d74b2d",
          "externalIds": {
            "MAG": "1986503899",
            "DOI": "10.1073/pnas.1211550109",
            "CorpusId": 11093198,
            "PubMed": "22869713"
          },
          "url": "https://www.semanticscholar.org/paper/e58a39cc21aedc818df66aa14225321977d74b2d",
          "title": "Kinetic mechanism of p53 oncogenic mutant aggregation and its inhibition",
          "venue": "Proceedings of the National Academy of Sciences of the United States of America",
          "year": 2012,
          "openAccessPdf": {
            "url": "https://www.pnas.org/content/pnas/109/34/13584.full.pdf",
            "status": "BRONZE",
            "license": null,
            "disclaimer": "Notice: The following paper fields have been elided by the publisher: {'abstract'}. Paper or abstract available at https://api.unpaywall.org/v2/10.1073/pnas.1211550109?email=<INSERT_YOUR_EMAIL> or https://doi.org/10.1073/pnas.1211550109, which is subject to the license by the author or copyright owner provided with this content. Please go to the source to verify the license and copyright information for your use."
          },
          "publicationTypes": [
            "JournalArticle"
          ],
          "publicationDate": "2012-08-06",
          "journal": {
            "name": "Proceedings of the National Academy of Sciences",
            "pages": "13584 - 13589",
            "volume": "109"
          },
          "authors": [
            {
              "authorId": "2268524",
              "name": "R. Wilcken"
            },
            {
              "authorId": "2145472159",
              "name": "Guozhen Wang"
            },
            {
              "authorId": "1831601",
              "name": "F. Boeckler"
            },
            {
              "authorId": "2384961",
              "name": "A. Fersht"
            }
          ],
          "abstract": null
        }
      ]
    }
  },
  "crossref": {
    "error": "",
    "metadata": null
  },
  "artifacts": {
    "record_path": "/Users/brandani/Dropbox/documents/library/paper_index/records/sha256-eabe48b38ae7610a.json",
    "text_path": "/Users/brandani/Dropbox/documents/library/paper_index/text/sha256-eabe48b38ae7610a.txt",
    "chunk_path": "/Users/brandani/Dropbox/documents/library/paper_index/chunks/sha256-eabe48b38ae7610a.jsonl",
    "master_index": "/Users/brandani/Dropbox/documents/library/paper_index/master_index.tsv",
    "master_bib": "/Users/brandani/Dropbox/documents/library/paper_index/master.bib",
    "text_kind": "pdf_text"
  },
  "text_extraction": {
    "status": "ok",
    "error": "",
    "text_sha256": "c6d01fc4f5a61b65df7c24211445dfdbb885c9d68bbe4835acc7b2e3b4fcea91",
    "chunk_count": 18,
    "chunk_target_chars": 2200,
    "chunk_overlap_chars": 250,
    "converter": "/Users/brandani/Dropbox/scripts/pdf2text.py"
  },
  "content_kind": "pdf_backed"
}
